lp/__init__.py
lp/cli.py
lp_loginparser-1.0.1.dist-info/licenses/LICENSE
lp_loginparser-1.0.1.dist-info/METADATA
lp_loginparser-1.0.1.dist-info/WHEEL
lp_loginparser-1.0.1.dist-info/entry_points.txt
lp_loginparser-1.0.1.dist-info/top_level.txt
lp_loginparser-1.0.1.dist-info/RECORD
